<?xml version="1.0" encoding="UTF-8"?>
<api context="/sample10" name="Sample10_API" xmlns="http://ws.apache.org/ns/synapse">
    <resource methods="POST">
        <inSequence>
            <datamapper config="gov:datamapper/Sample10DataMapperConfig.dmc" inputSchema="gov:datamapper/Sample10DataMapperConfig_inputSchema.json" inputType="XML" outputSchema="gov:datamapper/Sample10DataMapperConfig_outputSchema.json" outputType="XML" xsltStyleSheet="gov:datamapper/Sample10DataMapperConfig_xsltStyleSheet.xml"/>
            <respond/>
        </inSequence>
        <outSequence/>
        <faultSequence/>
    </resource>
</api>
